{
  "item_id": "1450",
  "item_name": "魔法石寶石(刻印)",
  "item_url": "https://www.gametsg.net/equip/detail.html?id=1450",
  "item_image": "https://www.gametsg.net/img/1/10/28a3d97f395664f657674b82fb9c4a39.jpg",
  "item_grade": "grade01",
  "item_comment": "38",
  "item_classes": [
    {
      "name": "全職業",
      "level": "class00"
    }
  ],
  "item_level": "-",
  "item_stats": [
    "神奇成分"
  ],
  "data_zhiye": "1000",
  "category_id": "37",
  "category_name": "材料",
  "basic_info": {
    "title": "魔法石寶石(刻印)",
    "類型": "其他(材料)",
    "職業": [
      {
        "name": "全職業",
        "level": "class00"
      }
    ],
    "材質": "原石",
    "重量": "0.2",
    "說明": "神奇成分"
  },
  "detail_info": {
    "倉庫": "可存倉",
    "交換": "無法交易"
  },
  "enhance_info": [],
  "craft_materials": [],
  "monster_drops": []
}